{
  "pack": "boss_4",
  "category": "boss",
  "source_pack": "4",
  "frame_count": 3,
  "sheet_width": 114,
  "sheet_height": 92,
  "scale": 2,
  "frames": [
    {
      "x": 0,
      "y": 9,
      "width": 28,
      "height": 74
    },
    {
      "x": 28,
      "y": 23,
      "width": 36,
      "height": 46
    },
    {
      "x": 64,
      "y": 0,
      "width": 50,
      "height": 92
    }
  ],
  "animations": {
    "walk": {
      "frames": [
        0
      ],
      "frameRate": 1,
      "repeat": -1
    }
  }
}