{
  "pack": "enm_02",
  "category": "enm",
  "source_pack": "02",
  "frame_count": 7,
  "sheet_width": 642,
  "sheet_height": 110,
  "scale": 2,
  "frames": [
    {
      "x": 0,
      "y": 16,
      "width": 126,
      "height": 78
    },
    {
      "x": 126,
      "y": 0,
      "width": 90,
      "height": 110
    },
    {
      "x": 216,
      "y": 23,
      "width": 130,
      "height": 64
    },
    {
      "x": 346,
      "y": 22,
      "width": 64,
      "height": 66
    },
    {
      "x": 410,
      "y": 16,
      "width": 62,
      "height": 78
    },
    {
      "x": 472,
      "y": 17,
      "width": 84,
      "height": 76
    },
    {
      "x": 556,
      "y": 16,
      "width": 86,
      "height": 78
    }
  ],
  "animations": {
    "walk": {
      "frames": [
        0,
        1,
        2,
        3
      ],
      "frameRate": 6,
      "repeat": -1
    },
    "attack": {
      "frames": [
        4,
        5
      ],
      "frameRate": 8,
      "repeat": 0
    },
    "hurt": {
      "frames": [
        6
      ],
      "frameRate": 4,
      "repeat": 0
    }
  }
}